cozo_client/__init__.py
cozo_client/_builder.py
cozo_client/_client.py
cozo_client-0.1.5.dist-info/METADATA
cozo_client-0.1.5.dist-info/WHEEL
cozo_client-0.1.5.dist-info/top_level.txt
cozo_client-0.1.5.dist-info/RECORD
